AUTHORS
LICENSE
MANIFEST.in
README.md
setup.cfg
setup.py
djedi/__init__.py
djedi/compat.py
djedi/models.py
djedi/urls.py
djedi/admin/__init__.py
djedi/admin/api.py
djedi/admin/cms.py
djedi/admin/exceptions.py
djedi/admin/mixins.py
djedi/admin/urls.py
djedi/auth/__init__.py
djedi/backends/__init__.py
djedi/backends/django/__init__.py
djedi/backends/django/cache/__init__.py
djedi/backends/django/cache/backend.py
djedi/backends/django/db/__init__.py
djedi/backends/django/db/backend.py
djedi/backends/django/db/models.py
djedi/middleware/__init__.py
djedi/middleware/admin.py
djedi/middleware/mixins.py
djedi/middleware/translation.py
djedi/migrations/0001_initial.py
djedi/migrations/0002_auto_20190722_1447.py
djedi/migrations/__init__.py
djedi/plugins/__init__.py
djedi/plugins/img.py
djedi/rest/__init__.py
djedi/rest/api.py
djedi/rest/urls.py
djedi/south_migrations/0001_initial.py
djedi/south_migrations/__init__.py
djedi/static/djedi/placeholder.svg
djedi/static/djedi/cms/js/cms.coffee
djedi/static/djedi/cms/js/cms.js
djedi/static/djedi/cms/js/uri.coffee
djedi/static/djedi/cms/js/uri.js
djedi/static/djedi/plugins/base/js/editor.coffee
djedi/static/djedi/plugins/base/js/editor.js
djedi/static/djedi/plugins/img/css/Jcrop.gif
djedi/static/djedi/plugins/img/css/img.css
djedi/static/djedi/plugins/img/css/jquery.Jcrop.min.css
djedi/static/djedi/plugins/img/js/img.coffee
djedi/static/djedi/plugins/img/js/img.js
djedi/static/djedi/plugins/img/js/jquery.Jcrop.min.js
djedi/static/djedi/plugins/img/js/jquery.fileupload-fp.js
djedi/static/djedi/plugins/img/js/jquery.fileupload-ui.js
djedi/static/djedi/plugins/img/js/jquery.fileupload.js
djedi/static/djedi/plugins/img/js/jquery.iframe-transport.js
djedi/static/djedi/plugins/img/js/jquery.ui.widget.js
djedi/static/djedi/themes/base/djedi-font.less
djedi/static/djedi/themes/base/flags.less
djedi/static/djedi/themes/base/flags.png
djedi/static/djedi/themes/base/fonts.less
djedi/static/djedi/themes/base/theme.less
djedi_cms.egg-info/PKG-INFO
djedi_cms.egg-info/SOURCES.txt
djedi_cms.egg-info/dependency_links.txt
djedi_cms.egg-info/not-zip-safe
djedi_cms.egg-info/requires.txt
djedi_cms.egg-info/top_level.txt