Metadata-Version: 2.1
Name: djedi-cms
Version: 1.3.3
Summary: Django content management as it should be
Home-page: https://github.com/5monkeys/djedi-cms
Author: Jonas Lundberg
Author-email: jonas@5monkeys.se
License: BSD
Download-URL: https://github.com/5monkeys/djedi-cms/tarball/1.3.3
Keywords: cms,django,edit,gettext,content,management,template,plugins,markdown
Platform: UNKNOWN
Classifier: Environment :: Web Environment
Classifier: Natural Language :: English
Classifier: Intended Audience :: Developers
Classifier: License :: OSI Approved :: BSD License
Classifier: Operating System :: OS Independent
Classifier: Programming Language :: Python
Classifier: Programming Language :: Python :: 2
Classifier: Programming Language :: Python :: 2.7
Classifier: Programming Language :: Python :: 3
Classifier: Programming Language :: Python :: 3.4
Classifier: Programming Language :: Python :: 3.5
Classifier: Programming Language :: Python :: 3.6
Classifier: Programming Language :: Python :: 3.7
Classifier: Topic :: Internet :: WWW/HTTP :: Dynamic Content
Classifier: Topic :: Software Development :: Libraries :: Python Modules
Provides-Extra: tests
